reapy/__init__.py
reapy/__init__.pyc
reapy/__init__.pyi
reapy/__main__.py
reapy/__main__.pyi
reapy/additional_api.py
reapy/config.pyc
reapy/errors.py
reapy/errors.pyc
reapy/errors.pyi
reapy/py.typed
reapy/reascript_api.py
reapy/reascript_api.pyi
reapy/__pycache__/__init__.cpython-35.pyc
reapy/__pycache__/__init__.cpython-37.pyc
reapy/__pycache__/__init__.cpython-38.pyc
reapy/__pycache__/__main__.cpython-37.pyc
reapy/__pycache__/additional_api.cpython-37.pyc
reapy/__pycache__/config.cpython-35.pyc
reapy/__pycache__/config.cpython-37.pyc
reapy/__pycache__/config.cpython-38.pyc
reapy/__pycache__/errors.cpython-35.pyc
reapy/__pycache__/errors.cpython-37.pyc
reapy/__pycache__/errors.cpython-38.pyc
reapy/__pycache__/reascript_api.cpython-37.pyc
reapy/__pycache__/reascript_api.cpython-38.pyc
reapy/config/__init__.py
reapy/config/config.py
reapy/config/config.pyi
reapy/config/resource_path.py
reapy/config/shared_library.py
reapy/config/__pycache__/__init__.cpython-37.pyc
reapy/config/__pycache__/__init__.cpython-38.pyc
reapy/config/__pycache__/config.cpython-37.pyc
reapy/config/__pycache__/config.cpython-38.pyc
reapy/config/__pycache__/python_sharedlib.cpython-37.pyc
reapy/config/__pycache__/resource_path.cpython-37.pyc
reapy/config/__pycache__/resource_path.cpython-38.pyc
reapy/config/__pycache__/shared_library.cpython-37.pyc
reapy/config/__pycache__/shared_library.cpython-38.pyc
reapy/core/__init__.py
reapy/core/__init__.pyi
reapy/core/audio_accessor.py
reapy/core/audio_accessor.pyi
reapy/core/envelope.py
reapy/core/envelope.pyi
reapy/core/reapy_object.py
reapy/core/reapy_object.pyi
reapy/core/__pycache__/__init__.cpython-35.pyc
reapy/core/__pycache__/__init__.cpython-37.pyc
reapy/core/__pycache__/__init__.cpython-38.pyc
reapy/core/__pycache__/audio_accessor.cpython-35.pyc
reapy/core/__pycache__/audio_accessor.cpython-37.pyc
reapy/core/__pycache__/audio_accessor.cpython-38.pyc
reapy/core/__pycache__/envelope.cpython-35.pyc
reapy/core/__pycache__/envelope.cpython-37.pyc
python_reapy-0.10.0.dist-info/LICENSE.txt
python_reapy-0.10.0.dist-info/METADATA
python_reapy-0.10.0.dist-info/WHEEL
python_reapy-0.10.0.dist-info/top_level.txt
python_reapy-0.10.0.dist-info/RECORD
