Metadata-Version: 2.1
Name: python-reapy
Version: 0.10.0
Summary: A pythonic wrapper for REAPER's ReaScript Python API
Home-page: UNKNOWN
Author: Roméo Després
Author-email: mail.reapy@gmail.com
License: MIT
Keywords: REAPER DAW ReaScript API wrapper music audio
Platform: UNKNOWN
Classifier: License :: OSI Approved :: MIT License
Classifier: Programming Language :: Python :: 3
Requires-Python: >=3.0
